instagram_creator_mcp/__init__.py
instagram_creator_mcp/instagram_api.py
instagram_creator_mcp/server.py
instagram_creator_mcp-1.0.0.dist-info/METADATA
instagram_creator_mcp-1.0.0.dist-info/WHEEL
instagram_creator_mcp-1.0.0.dist-info/entry_points.txt
instagram_creator_mcp-1.0.0.dist-info/RECORD
